{
  "name": "libblas",
  "version": "3.9.0",
  "build": "1_h8933c1f_netlib",
  "build_number": 1,
  "channel": "https://conda.anaconda.org/conda-forge/win-64",
  "subdir": "win-64",
  "fn": "libblas-3.9.0-1_h8933c1f_netlib.tar.bz2",
  "md5": "2c5ff3ea7416bb5edc70e67f4ee1ff71",
  "url": "https://conda.anaconda.org/conda-forge/win-64/libblas-3.9.0-1_h8933c1f_netlib.tar.bz2",
  "sha256": "250eb1a9b62490514a61aa0efc62638f44f6f3b7acd80b4b8eff66bd7319ce2c",
  "depends": [
    "m2w64-gcc-libs"
  ],
  "constrains": [
    "mkl <2025"
  ],
  "track_features": "blas_netlib blas_netlib_2",
  "license": "BSD-3-Clause",
  "timestamp": 1603053118509,
  "size": 198075,
  "_requested_specs": [],
  "package_tarball_full_path": "C:\\Users\\garvi\\.conda\\pkgs\\libblas-3.9.0-1_h8933c1f_netlib.tar.bz2",
  "extracted_package_dir": "C:\\Users\\garvi\\.conda\\pkgs\\libblas-3.9.0-1_h8933c1f_netlib",
  "files": [
    "Library/bin/libblas.dll",
    "Library/lib/blas.lib",
    "Library/lib/libblas.dll.a",
    "Library/lib/pkgconfig/blas.pc"
  ],
  "paths_data": {
    "paths_version": 1,
    "paths": [
      {
        "_path": "Library/bin/libblas.dll",
        "path_type": "hardlink",
        "sha256": "e56ac2c30e76ea7688fd4c892c4cda8b484ea3ef99a92c835739a1621d149dcf",
        "size_in_bytes": 524369,
        "sha256_in_prefix": "e56ac2c30e76ea7688fd4c892c4cda8b484ea3ef99a92c835739a1621d149dcf"
      },
      {
        "_path": "Library/lib/blas.lib",
        "path_type": "hardlink",
        "sha256": "0d0a86e559d7fb6590e60bf31494043d79a285a85fa26d5da1f186a5218b315a",
        "size_in_bytes": 25130,
        "sha256_in_prefix": "0d0a86e559d7fb6590e60bf31494043d79a285a85fa26d5da1f186a5218b315a"
      },
      {
        "_path": "Library/lib/libblas.dll.a",
        "path_type": "hardlink",
        "sha256": "1d9e7bc6781f0e3c9b58e2981113e3ff9f1f14cf6aa6e97183f1ce8c82de509f",
        "size_in_bytes": 86556,
        "sha256_in_prefix": "1d9e7bc6781f0e3c9b58e2981113e3ff9f1f14cf6aa6e97183f1ce8c82de509f"
      },
      {
        "_path": "Library/lib/pkgconfig/blas.pc",
        "prefix_placeholder": "D:/bld/blas-split_1603051246132/_h_env",
        "file_mode": "text",
        "path_type": "hardlink",
        "sha256": "b7bd1d05e99f6268014f0abf2c3a234f0fc26bbf9cd85f2d42c674b7db103f7d",
        "size_in_bytes": 304,
        "sha256_in_prefix": "2f4197a9bebdfaf28b3ad971ead1c479fbfb29b58e2961ac4632107550bec113"
      }
    ]
  },
  "link": {
    "source": "C:\\Users\\garvi\\.conda\\pkgs\\libblas-3.9.0-1_h8933c1f_netlib",
    "type": 1
  }
}